langgraph_responses_gateway/__init__.py
langgraph_responses_gateway/service.py
langgraph_responses_gateway/version.py
langgraph_responses_gateway/integrations/__init__.py
langgraph_responses_gateway/integrations/fastapi.py
langgraph_responses_gateway-2.0.2.dist-info/licenses/LICENSE
langgraph_responses_gateway-2.0.2.dist-info/METADATA
langgraph_responses_gateway-2.0.2.dist-info/WHEEL
langgraph_responses_gateway-2.0.2.dist-info/top_level.txt
langgraph_responses_gateway-2.0.2.dist-info/RECORD
