Metadata-Version: 2.4
Name: langgraph-responses-gateway
Version: 2.0.2
Summary: Expose any LangGraph agent as an OpenAI Responses API endpoint
Author: Jerome Mohanan
Maintainer: Jerome Mohanan
License-Expression: MIT
Project-URL: Homepage, https://github.com/jero2rome/langgraph-responses-gateway
Project-URL: Documentation, https://langgraph-responses-gateway.readthedocs.io
Project-URL: Repository, https://github.com/jero2rome/langgraph-responses-gateway
Project-URL: Issues, https://github.com/jero2rome/langgraph-responses-gateway/issues
Project-URL: Changelog, https://github.com/jero2rome/langgraph-responses-gateway/blob/main/CHANGELOG.md
Classifier: Development Status :: 3 - Alpha
Classifier: Intended Audience :: Developers
Classifier: Programming Language :: Python :: 3
Classifier: Programming Language :: Python :: 3.9
Classifier: Programming Language :: Python :: 3.10
Classifier: Programming Language :: Python :: 3.11
Classifier: Programming Language :: Python :: 3.12
Classifier: Topic :: Software Development :: Libraries :: Python Modules
Classifier: Topic :: Scientific/Engineering :: Artificial Intelligence
Requires-Python: >=3.9
License-File: LICENSE
Requires-Dist: pydantic>=2.0.0
Requires-Dist: langgraph>=0.5.0
Requires-Dist: typing-extensions>=4.0.0
Provides-Extra: web
Requires-Dist: fastapi>=0.100.0; extra == "web"
Requires-Dist: uvicorn>=0.23.0; extra == "web"
Requires-Dist: httpx>=0.24.0; extra == "web"
Provides-Extra: examples
Requires-Dist: fastapi>=0.100.0; extra == "examples"
Requires-Dist: uvicorn>=0.23.0; extra == "examples"
Requires-Dist: openai>=1.75.0; extra == "examples"
Provides-Extra: dev
Requires-Dist: pytest>=7.0.0; extra == "dev"
Requires-Dist: pytest-asyncio>=0.21.0; extra == "dev"
Requires-Dist: pytest-cov>=4.0.0; extra == "dev"
Requires-Dist: black>=23.0.0; extra == "dev"
Requires-Dist: ruff>=0.1.0; extra == "dev"
Requires-Dist: mypy>=1.0.0; extra == "dev"
Requires-Dist: types-requests; extra == "dev"
Provides-Extra: docs
Requires-Dist: mkdocs>=1.5.0; extra == "docs"
Requires-Dist: mkdocs-material>=9.0.0; extra == "docs"
Requires-Dist: mkdocstrings[python]>=0.24.0; extra == "docs"
Dynamic: license-file
